virtual_cursor/__init__.py
virtual_cursor/lona.py
virtual_cursor/playwright.py
virtual_cursor/pytest.py
virtual_cursor/virtual-cursor.js
virtual_cursor-0.1.dist-info/LICENSE.txt
virtual_cursor-0.1.dist-info/METADATA
virtual_cursor-0.1.dist-info/WHEEL
virtual_cursor-0.1.dist-info/entry_points.txt
virtual_cursor-0.1.dist-info/top_level.txt
virtual_cursor-0.1.dist-info/RECORD
