Metadata-Version: 2.1
Name: virtual-cursor
Version: 0.1
Summary: Write responsive web apps in full python
Author-email: Florian Scherf <mail@florianscherf.de>
License: MIT License
Project-URL: Homepage, https://github.com/fscherf/virtual-cursor
Project-URL: Repository, https://github.com/fscherf/virtual-cursor
Project-URL: Bug Tracker, https://github.com/fscherf/virtual-cursor/issues
Classifier: Development Status :: 5 - Production/Stable
Classifier: Environment :: Web Environment
Classifier: Framework :: AsyncIO
Classifier: Framework :: Django
Classifier: Framework :: Pytest
Classifier: License :: OSI Approved :: MIT License
Classifier: Natural Language :: English
Classifier: Operating System :: Unix
Classifier: Programming Language :: JavaScript
Classifier: Programming Language :: Python :: 3 :: Only
Classifier: Topic :: Internet
Classifier: Topic :: Internet :: WWW/HTTP
Classifier: Topic :: Internet :: WWW/HTTP :: Dynamic Content
Requires-Python: >=3.8
License-File: LICENSE.txt
Provides-Extra: dev
Requires-Dist: build ; extra == 'dev'
Requires-Dist: twine ; extra == 'dev'
Requires-Dist: tox ; extra == 'dev'
Requires-Dist: lona ==1.15 ; extra == 'dev'
Requires-Dist: lona-picocss ==0.4.1 ; extra == 'dev'
Requires-Dist: coverage ==7.2.7 ; extra == 'dev'
Requires-Dist: pytest ==7.4.0 ; extra == 'dev'
Requires-Dist: pytest-aiohttp ==1.0.4 ; extra == 'dev'
Requires-Dist: pytest-timeout ==2.1.0 ; extra == 'dev'
Requires-Dist: playwright ==1.36.0 ; extra == 'dev'
